gapclean/__init__.py
gapclean/gapclean.py
gapclean-1.0.2.dist-info/LICENSE
gapclean-1.0.2.dist-info/METADATA
gapclean-1.0.2.dist-info/WHEEL
gapclean-1.0.2.dist-info/entry_points.txt
gapclean-1.0.2.dist-info/top_level.txt
gapclean-1.0.2.dist-info/RECORD
