Metadata-Version: 2.1
Name: gapclean
Version: 1.0.2
Summary: Clean up large gappy multiple sequence alignments.
Author: Aarya Venkat, PhD
Project-URL: Github, https://github.com/arikat/GapClean
Project-URL: Homepage, https://aaryakat.com
Keywords: sequence alignment,bioinformatics, computational biology, protein
Classifier: Programming Language :: Python :: 3
Classifier: License :: OSI Approved :: MIT License
Classifier: Operating System :: OS Independent
Requires-Python: >=3.8
License-File: LICENSE
Requires-Dist: tqdm
Requires-Dist: numpy
